lbox/call_info.py
lbox/exceptions.py
lbox/request_client.py
lbox_clients-1.1.2.dist-info/METADATA
lbox_clients-1.1.2.dist-info/WHEEL
lbox_clients-1.1.2.dist-info/RECORD
